Metadata-Version: 2.1
Name: czbag_code
Version: 0.0.1
Summary: Test Project
Author-email: czbag.ton@proton.me
